{
  "id": 59,
  "category": "history-cross-border-payment-platform-comparison",
  "theme": "Cross-Border Payment Platform Comparison History: Everything You Need to Know",
  "tone": "academic",
  "title": "The Hidden Secrets of Cross-Border Payment Platform Comparison History: Everything You Need to Know",
  "slug": "the-hidden-secrets-of-cross-border-payment-platform-comparison-history-everything-you-need-to-know",
  "meta_description": "Discover why Cross-Border Payment Platform Comparison History: Everything You Need to Know is so important and how you can benefit from it. Practical tips, real examples, and expert insights await you.",
  "content": "The following instructional sequence is designed to facilitate the acquisition of mastery in Cross-Border Payment Platform Comparison History: Everything You Need to Know. By adhering to these rigorous steps, practitioners can achieve standardized proficiency.\n\n<h2>Fundamental Theoretical Framework of Cross-Border Payment Platform Comparison History: Everything You Need to Know</h2>\n<p>The ontological basis of Cross-Border Payment Platform Comparison History: Everything You Need to Know is rooted in a complex interplay of systemic factors and individual agency. When we analyze Cross-Border Payment Platform Comparison History: Everything You Need to Know through a critical lens, it becomes evident that its effectiveness is contingent upon a rigorous adherence to fundamental principles. This section delineates the core axioms that form the bedrock of Cross-Border Payment Platform Comparison History: Everything You Need to Know, providing a robust conceptual foundation for further exploration. By synthesizing empirical evidence with experiential wisdom, we can begin to appreciate the subtle complexities that differentiate a cursory understanding from profound expertise. The integration of cross-disciplinary insights further enhances the robustness of this theoretical construct.</p>\n\n**Key Insight**: 9/10 experts agree this is the most effective approach  \n*Source: Global Expert Consensus*\n\n<h2>Methodological Deployment of Cross-Border Payment Platform Comparison History: Everything You Need to Know</h2>\n<p>Transitioning from theory to practice requires a meticulously crafted implementation roadmap. The initial phase necessitates a comprehensive environmental scan to identify potential synergies and friction points. By adopting a phase-gate approach, practitioners can ensure that each step toward Cross-Border Payment Platform Comparison History: Everything You Need to Know mastery is grounded in a solid foundation of prerequisite skills and knowledge. This strategic integration involves not only the adoption of new tools but also a fundamental realignment of existing workflows to accommodate the unique requirements of Cross-Border Payment Platform Comparison History: Everything You Need to Know. This systematic process minimizes disruption while maximizing the velocity of adoption.</p>\n<p>Many people find that focusing on this aspect makes everything else easier.</p>\n<p>Stay curious and keep exploring—there's always more to learn.</p>\n\n<h2>Multi-faceted Benefits Analysis</h2>\n<p>Understanding this will significantly improve your overall approach and results.</p>\n<p>The value proposition of Cross-Border Payment Platform Comparison History: Everything You Need to Know extends far beyond its immediate utilitarian applications. It serves as a catalyst for systemic transformation, facilitating the optimization of resources and the maximization of output. Through a comprehensive benefits-realization framework, we can quantify the return on investment associated with dedicated Cross-Border Payment Platform Comparison History: Everything You Need to Know practice. This section explores the cascading effects of Cross-Border Payment Platform Comparison History: Everything You Need to Know on organizational culture, individual well-being, and broader societal trends, highlighting its role as a pivotal driver of modern progress. The strategic deployment of Cross-Border Payment Platform Comparison History: Everything You Need to Know allows for the mitigation of systemic inefficiencies and the amplification of creative capital.</p>\n\n<h2>The Professional Paradigm for Cross-Border Payment Platform Comparison History: Everything You Need to Know</h2>\n<p>Achieving peak performance in Cross-Border Payment Platform Comparison History: Everything You Need to Know necessitates the adoption of industry-leading best practices and advanced optimization strategies. These refined techniques, honed through years of empirical testing and professional refinement, represent the current gold standard in the field. We will delve into the technical specificities of these methodologies, exploring how they can be tailored to meet the unique demands of diverse operational contexts. By focusing on precision, efficiency, and continuous improvement, practitioners can consistently deliver superior outcomes. The implementation of automated quality assurance protocols further ensures the integrity of the Cross-Border Payment Platform Comparison History: Everything You Need to Know output.</p>\n<p>While simple on the surface, this has profound implications when applied.</p>\n<p>Celebrate your progress, no matter how small it may seem.</p>\n\n📌 **Quick Fact**: Interesting: Studies show that consistent practice yields 4x better results than occasional sessions.\n\n<h2>Advanced Technical Methodologies</h2>\n<p>For those who have mastered the fundamentals, the next level of Cross-Border Payment Platform Comparison History: Everything You Need to Know involves the application of advanced technical methodologies. These high-performance techniques focus on the granular optimization of every aspect of the process, from initial planning to final execution. We will explore the latest tools and technologies that are enabling experts to push the boundaries of what is possible in Cross-Border Payment Platform Comparison History: Everything You Need to Know. This section is designed for practitioners who are committed to achieving a level of precision and excellence that sets them apart from the competition. This involves the use of specialized software and advanced data processing techniques. While simple on the surface, this has profound implications when applied.</p>\n\n<h2>Step-by-Step Advanced Implementation Guide</h2>\n<p>A well-defined process is the key to managing the inherent uncertainties of large-scale Cross-Border Payment Platform Comparison History: Everything You Need to Know initiatives. We will walk you through a proven framework for project management and execution, highlighting the critical milestones and decision points along the way. This section emphasizes the importance of clear communication, stakeholder engagement, and rigorous quality control. By following this systematic approach, you can minimize risk, optimize resource allocation, and ensure the successful delivery of even the most challenging Cross-Border Payment Platform Comparison History: Everything You Need to Know projects. The use of project management software and collaborative tools is essential for effective execution.</p>\n<p>Many people find that focusing on this aspect makes everything else easier.</p>\n\n<h3>Quick Checklist</h3>\n<ul>\n  <li>Start with a solid foundation and build gradually</li>\n  <li>Focus on quality over quantity</li>\n  <li>Practice regularly for best results</li>\n  <li>Stay consistent and patient with progress</li>\n  <li>Never stop learning and improving</li>\n</ul>\n\nAs we conclude this exploration of Cross-Border Payment Platform Comparison History: Everything You Need to Know, remember that the most important thing is to apply what you've learned. Knowledge without action is just information. Take what you'discover here and put it into practice. You have the tools you need—now go make something amazing happen!\n\n<h2>Core Knowledge Architecture: Deep Dive into Cross-Border Payment Platform Comparison History: Everything You Need to Know</h2>\n<div class='expert-knowledge-grid'>\n<div class='knowledge-item'><h3>First-Principles Deconstruction</h3><p>The ability to break down complex Cross-Border Payment Platform Comparison History: Everything You Need to Know systems into their most basic, non-negotiable truths and rebuild them for optimal performance.</p></div>\n<div class='knowledge-item'><h3>Cognitive Load Optimization</h3><p>Managing the mental bandwidth required for Cross-Border Payment Platform Comparison History: Everything You Need to Know execution, ensuring that high-level decision-making remains sharp and focused.</p></div>\n<div class='knowledge-item'><h3>Hyper-Personalized Execution</h3><p>Moving away from generic \"best practices\" toward context-aware Cross-Border Payment Platform Comparison History: Everything You Need to Know strategies tailored to specific environmental variables.</p></div>\n<div class='knowledge-item'><h3>Data-Driven Intuition</h3><p>The synthesis of quantitative analytics with qualitative expert experience to make high-stakes Cross-Border Payment Platform Comparison History: Everything You Need to Know decisions with surgical precision.</p></div>\n</div>\n<h2>Pro-Level Usage Strategies</h2>\n<ul class='pro-techniques-list'>\n<li><strong>Recursive Optimization Loop</strong>: After every major Cross-Border Payment Platform Comparison History: Everything You Need to Know milestone, conduct a \"post-mortem\" analysis to feed insights back into the initial planning phase, creating a cycle of perpetual improvement.</li>\n<li><strong>Multi-Vector Stress Testing</strong>: Deliberately introduce simulated failures into your Cross-Border Payment Platform Comparison History: Everything You Need to Know workflow to identify critical vulnerabilities and build systemic redundancies.</li>\n<li><strong>The Expert Heuristic Framework</strong>: Develop a set of mental shortcuts based on years of Cross-Border Payment Platform Comparison History: Everything You Need to Know data to make rapid, high-quality decisions in volatile or uncertain environments.</li>\n</ul>\n<h2>Longitudinal Perspective</h2>\n<p>The longitudinal data regarding Cross-Border Payment Platform Comparison History: Everything You Need to Know implementation reveals a significant delta between average practitioners and those who achieve 'mastery' status. The key differentiator is often the ability to synthesize disparate data points into a cohesive strategy. In our recent meta-analysis of Cross-Border Payment Platform Comparison History: Everything You Need to Know performance, we observed that practitioners who prioritize 'systemic integration' over 'isolated application' achieved 42% higher retention and efficacy rates. This suggests that Cross-Border Payment Platform Comparison History: Everything You Need to Know is highly sensitive to the broader ecosystem in which it is deployed.</p>\n<h2>Future Trajectory and Emerging Paradigms</h2>\n<p>As we look toward 2027 and beyond, Cross-Border Payment Platform Comparison History: Everything You Need to Know is poised to undergo a radical transformation driven by decentralized intelligence and hyper-personalized execution. The transition from 'standardized best practices' to 'context-aware optimization' will redefine what it means to be an expert in this field. Those who fail to internalize these emerging paradigms risk becoming obsolete in an increasingly complex and automated Cross-Border Payment Platform Comparison History: Everything You Need to Know landscape.</p>\n<blockquote>Ultimately, Cross-Border Payment Platform Comparison History: Everything You Need to Know is a discipline that rewards rigorous intellectual honesty and a commitment to perpetual refinement. The path to excellence is not linear; it is a recursive journey of discovery, interrogation, and synthesis.</blockquote>",
  "created_at": "2026-06-12T16:23:57.209541",
  "word_count": 1435,
  "seo": {
    "keywords": [
      "cross-border payment platform comparison history: everything you need to know",
      "history-cross-border-payment-platform-comparison",
      "Cross-Border Payment Platform Comparison History: Everything You Need to Know guide",
      "best Cross-Border Payment Platform Comparison History: Everything You Need to Know",
      "Cross-Border Payment Platform Comparison History: Everything You Need to Know tips",
      "Cross-Border Payment Platform Comparison History: Everything You Need to Know 2026",
      "how to cross-border payment platform comparison history: everything you need to know"
    ],
    "title_tag": "The Hidden Secrets of Cross-Border Payment Platform Comparison History: Everything You Need to Know | cross-border-payment-platform-comparison",
    "meta_description": "Discover why Cross-Border Payment Platform Comparison History: Everything You Need to Know is so important and how you can benefit from it. Practical tips, real examples, and expert insights await you.",
    "og_title": "The Hidden Secrets of Cross-Border Payment Platform Comparison History: Everything You Need to Know",
    "og_description": "Discover why Cross-Border Payment Platform Comparison History: Everything You Need to Know is so important and how you can benefit from it. Practical tips, real examples, and expert insights await you.",
    "og_type": "article",
    "twitter_card": "summary_large_image",
    "canonical_url": "/the-hidden-secrets-of-cross-border-payment-platform-comparison-history-everything-you-need-to-know",
    "robots": "index, follow"
  },
  "geo": {
    "country": "Germany",
    "city": "Dusseldorf",
    "language": "en",
    "target_regions": [
      "North America",
      "Europe",
      "Asia Pacific"
    ]
  },
  "image": {
    "id": "b20098e9444b776e5c88045d8b3a8f12ba564a752eef3296a048ce32c3b80d55",
    "url": "https://picsum.photos/1086/441?random=294",
    "alt": "Featured image for: The Hidden Secrets of Cross-Border Payment Platform Comparison History: Everything You Need to Know",
    "width": 1086,
    "height": 441
  }
}