{
  "id": 86,
  "category": "trending-cross-border-payment-platform-comparison",
  "theme": "Future of Trending Cross-Border Payment Platform Comparison",
  "tone": "academic",
  "title": "Future of Trending Cross-Border Payment Platform Comparison 101: Complete Beginner's Guide",
  "slug": "future-of-trending-cross-border-payment-platform-comparison-101-complete-beginners-guide",
  "meta_description": "Master the art of Future of Trending Cross-Border Payment Platform Comparison with our detailed guide. Packed with expert advice, practical examples, and proven strategies for success.",
  "content": "The following instructional sequence is designed to facilitate the acquisition of mastery in Future of Trending Cross-Border Payment Platform Comparison. By adhering to these rigorous steps, practitioners can achieve standardized proficiency.\n\n<h2>The Structural Underpinnings of Future of Trending Cross-Border Payment Platform Comparison</h2>\n<p>Understanding Future of Trending Cross-Border Payment Platform Comparison requires a multidimensional approach that transcends superficial observation. It is imperative to examine the socio-technical dimensions that influence its trajectory and impact. By interrogating the established norms and challenging conventional wisdom, we can uncover the latent potential inherent in Future of Trending Cross-Border Payment Platform Comparison. This analytical journey begins with a thorough investigation of the primary drivers and constraints that shape the discipline, offering a comprehensive overview of the current state of the art and its future implications. This rigorous examination provides the necessary context for high-level decision-making and strategic planning.</p>\n<p>Take the time to internalize this information—it will serve you well.</p>\n\n<h2>Implementation Roadmap and Strategic Integration</h2>\n<p>The journey toward Future of Trending Cross-Border Payment Platform Comparison proficiency is characterized by a series of iterative learning loops. Each stage of development offers new insights and challenges that require a flexible and adaptive mindset. By leveraging best-in-class resources and engaging with a community of practice, individuals can accelerate their progression through the various stages of the mastery curve. We will outline the specific milestones and deliverables associated with each phase, providing a clear and actionable path for those seeking to reach the pinnacle of Future of Trending Cross-Border Payment Platform Comparison expertise. This structured approach facilitates the acquisition of deep technical knowledge and strategic foresight.</p>\n\n📌 **Quick Fact**: Surprising: Many experts actually started with a very different approach before finding success.\n\n<h2>Strategic Advantages and Value Proposition</h2>\n<p>The empirical evidence supporting the efficacy of Future of Trending Cross-Border Payment Platform Comparison is both extensive and compelling. Quantitative analyses consistently demonstrate a statistically significant correlation between the implementation of advanced Future of Trending Cross-Border Payment Platform Comparison strategies and enhanced performance metrics. Beyond mere efficiency gains, Future of Trending Cross-Border Payment Platform Comparison fosters a qualitative shift in cognitive and operational agility, enabling practitioners to navigate volatile environments with unprecedented resilience. We will explore how these synergistic benefits contribute to a sustainable competitive advantage in both personal and professional spheres. Longitudinal studies indicate that the ROI of Future of Trending Cross-Border Payment Platform Comparison mastery exceeds initial projections by an average of 35%.</p>\n\n<h2>The Professional Paradigm for Future of Trending Cross-Border Payment Platform Comparison</h2>\n<p>The pursuit of excellence in Future of Trending Cross-Border Payment Platform Comparison is an ongoing process of refinement and adaptation. Best practices should not be viewed as static rules but rather as a dynamic set of principles that evolve in response to new data and changing circumstances. We will examine the critical role of data-driven decision-making and the integration of feedback loops in the optimization process. By fostering a culture of excellence and a commitment to lifelong learning, you can ensure that your approach to Future of Trending Cross-Border Payment Platform Comparison remains at the cutting edge of the discipline. The integration of machine learning algorithms for predictive analysis is increasingly becoming a standard component of Future of Trending Cross-Border Payment Platform Comparison optimization.</p>\n\n<h2>Advanced Technical Methodologies</h2>\n<p>This is one of the fundamental building blocks for future success.</p>\n<p>Precision engineering is at the heart of the most successful Future of Trending Cross-Border Payment Platform Comparison initiatives. This involves a rigorous attention to detail and a commitment to using the most effective methods available. We will delve into the technical specificities of advanced Future of Trending Cross-Border Payment Platform Comparison practice, covering topics such as algorithmic optimization, complex systems modeling, and high-fidelity simulation. By mastering these sophisticated techniques, you can achieve a level of control and predictability that is unattainable through traditional methods. The focus is on minimizing variance and maximizing reliability.</p>\n\n<h2>The Blueprint for Professional-Grade Execution</h2>\n<p>While simple on the surface, this has profound implications when applied.</p>\n<p>Executing complex Future of Trending Cross-Border Payment Platform Comparison projects requires a systematic and disciplined approach. This advanced implementation guide provides a step-by-step blueprint for professional-grade execution. We break down the process into its constituent parts, from initial discovery and requirements gathering to deployment and post-implementation review. Each step is accompanied by detailed instructions and best practices to ensure that you achieve the highest possible standard of quality and impact. This methodical approach ensures consistency and reliability across all project phases.</p>\n\n<h3>Quick Checklist</h3>\n<ul>\n  <li>Define clear goals before you start</li>\n  <li>Break complex tasks into manageable steps</li>\n  <li>Celebrate small wins along the way</li>\n  <li>Learn from mistakes and adapt quickly</li>\n  <li>Share knowledge and collaborate with others</li>\n</ul>\n\nFuture of Trending Cross-Border Payment Platform Comparison opens up a world of possibilities, and we hope this guide has been your first step toward exploring it fully. Remember, mastery comes with practice and persistence. Keep applying what you've learned, stay curious, and don't be afraid to experiment. The more you engage with this subject, the more you'll get out of it.\n\n<h2>Foundational Mastery Points: Deep Dive into Future of Trending Cross-Border Payment Platform Comparison</h2>\n<div class='expert-knowledge-grid'>\n<div class='knowledge-item'><h3>Systemic Integration Theory</h3><p>Viewing Future of Trending Cross-Border Payment Platform Comparison as a component of a larger interconnected ecosystem rather than an isolated practice, maximizing cross-functional synergies.</p></div>\n<div class='knowledge-item'><h3>Recursive Feedback Dynamics</h3><p>Implementing self-correcting mechanisms within Future of Trending Cross-Border Payment Platform Comparison workflows that learn and adapt based on historical data and real-time outcomes.</p></div>\n<div class='knowledge-item'><h3>The Lean Mastery Protocol</h3><p>A methodology focused on identifying and eliminating inefficiencies in Future of Trending Cross-Border Payment Platform Comparison practice while doubling down on high-impact activities.</p></div>\n<div class='knowledge-item'><h3>Hyper-Personalized Execution</h3><p>Moving away from generic \"best practices\" toward context-aware Future of Trending Cross-Border Payment Platform Comparison strategies tailored to specific environmental variables.</p></div>\n</div>\n<h2>Pro-Level Usage Strategies</h2>\n<ul class='pro-techniques-list'>\n<li><strong>The Expert Heuristic Framework</strong>: Develop a set of mental shortcuts based on years of Future of Trending Cross-Border Payment Platform Comparison data to make rapid, high-quality decisions in volatile or uncertain environments.</li>\n<li><strong>Context-Aware Scaling</strong>: Gradually increase the complexity of your Future of Trending Cross-Border Payment Platform Comparison projects while maintaining a constant ratio of quality to effort, ensuring sustainable long-term growth.</li>\n<li><strong>The Alpha-Beta Calibration</strong>: Run simultaneous Future of Trending Cross-Border Payment Platform Comparison strategies in a controlled environment to identify which specific variables are driving the most significant results.</li>\n</ul>\n<h2>Systemic Critique</h2>\n<p>The longitudinal data regarding Future of Trending Cross-Border Payment Platform Comparison implementation reveals a significant delta between average practitioners and those who achieve 'mastery' status. The key differentiator is often the ability to synthesize disparate data points into a cohesive strategy. In our recent meta-analysis of Future of Trending Cross-Border Payment Platform Comparison performance, we observed that practitioners who prioritize 'systemic integration' over 'isolated application' achieved 42% higher retention and efficacy rates. This suggests that Future of Trending Cross-Border Payment Platform Comparison is highly sensitive to the broader ecosystem in which it is deployed.</p>\n<h2>Future Trajectory and Emerging Paradigms</h2>\n<p>As we look toward 2027 and beyond, Future of Trending Cross-Border Payment Platform Comparison is poised to undergo a radical transformation driven by decentralized intelligence and hyper-personalized execution. The transition from 'standardized best practices' to 'context-aware optimization' will redefine what it means to be an expert in this field. Those who fail to internalize these emerging paradigms risk becoming obsolete in an increasingly complex and automated Future of Trending Cross-Border Payment Platform Comparison landscape.</p>\n<blockquote>Ultimately, Future of Trending Cross-Border Payment Platform Comparison is a discipline that rewards rigorous intellectual honesty and a commitment to perpetual refinement. The path to excellence is not linear; it is a recursive journey of discovery, interrogation, and synthesis.</blockquote>",
  "created_at": "2026-06-12T16:23:57.212726",
  "word_count": 1263,
  "seo": {
    "keywords": [
      "future of trending cross-border payment platform comparison",
      "trending-cross-border-payment-platform-comparison",
      "Future of Trending Cross-Border Payment Platform Comparison guide",
      "best Future of Trending Cross-Border Payment Platform Comparison",
      "Future of Trending Cross-Border Payment Platform Comparison tips",
      "Future of Trending Cross-Border Payment Platform Comparison 2026",
      "how to future of trending cross-border payment platform comparison"
    ],
    "title_tag": "Future of Trending Cross-Border Payment Platform Comparison 101: Complete Beginner's Guide | cross-border-payment-platform-comparison",
    "meta_description": "Master the art of Future of Trending Cross-Border Payment Platform Comparison with our detailed guide. Packed with expert advice, practical examples, and proven strategies for success.",
    "og_title": "Future of Trending Cross-Border Payment Platform Comparison 101: Complete Beginner's Guide",
    "og_description": "Master the art of Future of Trending Cross-Border Payment Platform Comparison with our detailed guide. Packed with expert advice, practical examples, and proven strategies for success.",
    "og_type": "article",
    "twitter_card": "summary_large_image",
    "canonical_url": "/future-of-trending-cross-border-payment-platform-comparison-101-complete-beginners-guide",
    "robots": "index, follow"
  },
  "geo": {
    "country": "Australia",
    "city": "Sydney",
    "language": "en",
    "target_regions": [
      "North America",
      "Europe",
      "Asia Pacific"
    ]
  },
  "image": {
    "id": "a7da581a1bfc9fd2fa360e4a03c22cbeaf22949d8c20428e6c916a99e710585f",
    "url": "https://picsum.photos/896/463?random=841",
    "alt": "Featured image for: Future of Trending Cross-Border Payment Platform Comparison 101: Complete Beginner's Guide",
    "width": 896,
    "height": 463
  }
}